hjcalc/jipack.py
hjcalc/setup.py
jeongin00-0.0.1.dist-info/METADATA
jeongin00-0.0.1.dist-info/WHEEL
jeongin00-0.0.1.dist-info/top_level.txt
jeongin00-0.0.1.dist-info/RECORD
